{
  "dataList": [
    {
      "id": 912014,
      "stageList": [
        {
          "id": 912001,
          "title": "Глубины Мэрс"
        },
        {
          "id": 912002,
          "title": "Глубины Мэрс"
        },
        {
          "id": 912003,
          "title": "Глубины Мэрс"
        },
        {
          "id": 912004,
          "title": "Глубины Мэрс"
        },
        {
          "id": 912005,
          "title": "Глубины Мэрс"
        },
        {
          "id": 912006,
          "title": "Глубины Мэрс"
        },
        {
          "id": 912007,
          "title": "Глубины Мэрс"
        },
        {
          "id": 912008,
          "title": "Глубины Мэрс"
        },
        {
          "id": 912009,
          "title": "Глубины Мэрс"
        },
        {
          "id": 912010,
          "title": "Глубины Мэрс"
        },
        {
          "id": 912011,
          "title": "Глубины Мэрс"
        },
        {
          "id": 912012,
          "title": "Глубины Мэрс"
        },
        {
          "id": 912013,
          "title": "Глубины Мэрс"
        },
        {
          "id": 912014,
          "title": "Глубины Мэрс"
        },
        {
          "id": 912015,
          "title": "Глубины Мэрс"
        },
        {
          "id": 912016,
          "title": "Глубины Мэрс"
        }
      ]
    }
  ]
}